odoo9_addon_website_sale_wishlist-9.0.1.0.0-py2.7-nspkg.pth
odoo_addons/website_sale_wishlist/__openerp__.py
odoo_addons/website_sale_wishlist/__init__.py
odoo_addons/website_sale_wishlist/README.rst
odoo_addons/website_sale_wishlist/security/ir.rule.csv
odoo_addons/website_sale_wishlist/security/ir.model.access.csv
odoo_addons/website_sale_wishlist/models/product_template.py
odoo_addons/website_sale_wishlist/models/product_wishlist.py
odoo_addons/website_sale_wishlist/models/__init__.py
odoo_addons/website_sale_wishlist/models/website.py
odoo_addons/website_sale_wishlist/models/res_users.py
odoo_addons/website_sale_wishlist/i18n/es.po
odoo_addons/website_sale_wishlist/views/shop.xml
odoo_addons/website_sale_wishlist/views/layout.xml
odoo_addons/website_sale_wishlist/views/assets.xml
odoo_addons/website_sale_wishlist/controllers/main.py
odoo_addons/website_sale_wishlist/controllers/__init__.py
odoo_addons/website_sale_wishlist/data/ir_cron.yml
odoo_addons/website_sale_wishlist/tests/__init__.py
odoo_addons/website_sale_wishlist/tests/test_ui.py
odoo_addons/website_sale_wishlist/demo/assets.xml
odoo_addons/website_sale_wishlist/static/description/icon.png
odoo_addons/website_sale_wishlist/static/src/js/wishlist_toggle.js
odoo_addons/website_sale_wishlist/static/src/js/wishlist_tour.js
odoo9_addon_website_sale_wishlist-9.0.1.0.0.dist-info/top_level.txt
odoo9_addon_website_sale_wishlist-9.0.1.0.0.dist-info/WHEEL
odoo9_addon_website_sale_wishlist-9.0.1.0.0.dist-info/RECORD
odoo9_addon_website_sale_wishlist-9.0.1.0.0.dist-info/metadata.json
odoo9_addon_website_sale_wishlist-9.0.1.0.0.dist-info/DESCRIPTION.rst
odoo9_addon_website_sale_wishlist-9.0.1.0.0.dist-info/METADATA
odoo9_addon_website_sale_wishlist-9.0.1.0.0.dist-info/namespace_packages.txt
