Metadata-Version: 2.0
Name: odoo9-addon-website-sale-wishlist
Version: 9.0.1.0.0
Summary: Wishlist of products in your online shop
Home-page: https://tecnativa.com/
Author: UNKNOWN
Author-email: UNKNOWN
License: LGPL-3
Platform: UNKNOWN
Requires-Dist: odoo (<9.1a,>=9.0a)
Classifier: Programming Language :: Python :: 2.7
Classifier: Framework :: Odoo
Classifier: License :: OSI Approved :: GNU Lesser General Public License v3 (LGPLv3)
